MockSSH.py
MockSSH-1.4.5.data/scripts/mock.hy
MockSSH-1.4.5.data/scripts/mock_F5.py
MockSSH-1.4.5.data/scripts/mock_cisco.py
MockSSH-1.4.5.dist-info/DESCRIPTION.rst
MockSSH-1.4.5.dist-info/METADATA
MockSSH-1.4.5.dist-info/RECORD
MockSSH-1.4.5.dist-info/WHEEL
MockSSH-1.4.5.dist-info/metadata.json
MockSSH-1.4.5.dist-info/top_level.txt
mocksshy/__init__.py
mocksshy/kwzip.hy
mocksshy/language.hy
