Metadata-Version: 1.1
Name: MockSSH
Version: 1.4.5
Summary: MockSSH: Mock an SSH server and all commands it supports.
Home-page: https://github.com/ncouture/MockSSH
Author: Nicolas Couture
Author-email: nicolas.couture@gmail.com
License: BSD
Keywords: ssh server emulation,ssh server testing,mock ssh,script ssh
Platform: Posix
Platform: MacOS X
Platform: Windows
Classifier: Development Status :: 5 - Production/Stable
Classifier: Intended Audience :: Developers
Classifier: License :: OSI Approved :: BSD License
Classifier: Programming Language :: Python :: 2.7
Classifier: Framework :: Twisted
Classifier: Environment :: Console
Classifier: Operating System :: POSIX
Classifier: Operating System :: MacOS :: MacOS X
Classifier: Operating System :: Microsoft :: Windows
Classifier: Topic :: Software Development :: Testing
Classifier: Topic :: System :: Emulators
